{
    "swagger": "2.0",
    "info": {
        "contact": {}
    },
    "paths": {
        "/leads": {
            "get": {
                "consumes": [
                    "application/json"
                ],
                "produces": [
                    "application/json"
                ],
                "tags": [
                    "Lead"
                ],
                "parameters": [
                    {
                        "type": "string",
                        "name": "keyword",
                        "in": "query",
                        "required": true
                    },
                    {
                        "minimum": 10,
                        "type": "integer",
                        "name": "limit",
                        "in": "query"
                    },
                    {
                        "minimum": 0,
                        "type": "integer",
                        "name": "skip",
                        "in": "query"
                    }
                ],
                "responses": {
                    "200": {
                        "description": "OK",
                        "schema": {
                            "$ref": "#/definitions/services.LeadPagination"
                        }
                    }
                }
            },
            "post": {
                "consumes": [
                    "application/json"
                ],
                "produces": [
                    "application/json"
                ],
                "tags": [
                    "Lead"
                ],
                "parameters": [
                    {
                        "description": "Create Lead",
                        "name": "lead",
                        "in": "body",
                        "required": true,
                        "schema": {
                            "$ref": "#/definitions/validation.CreateLead"
                        }
                    }
                ],
                "responses": {
                    "200": {
                        "description": "OK",
                        "schema": {
                            "$ref": "#/definitions/entities.Lead"
                        }
                    }
                }
            }
        },
        "/leads/{id}": {
            "get": {
                "consumes": [
                    "application/json"
                ],
                "produces": [
                    "application/json"
                ],
                "tags": [
                    "Lead"
                ],
                "parameters": [
                    {
                        "type": "string",
                        "description": "Find Lead By ID",
                        "name": "id",
                        "in": "path",
                        "required": true
                    }
                ],
                "responses": {
                    "200": {
                        "description": "OK",
                        "schema": {
                            "$ref": "#/definitions/entities.Lead"
                        }
                    }
                }
            },
            "put": {
                "consumes": [
                    "application/json"
                ],
                "produces": [
                    "application/json"
                ],
                "tags": [
                    "Lead"
                ],
                "parameters": [
                    {
                        "type": "string",
                        "description": "Update By ID",
                        "name": "id",
                        "in": "path",
                        "required": true
                    },
                    {
                        "description": "Update Lead",
                        "name": "lead",
                        "in": "body",
                        "required": true,
                        "schema": {
                            "$ref": "#/definitions/validation.UpdateLead"
                        }
                    }
                ],
                "responses": {
                    "200": {
                        "description": "OK",
                        "schema": {
                            "$ref": "#/definitions/entities.Lead"
                        }
                    }
                }
            },
            "delete": {
                "consumes": [
                    "application/json"
                ],
                "produces": [
                    "application/json"
                ],
                "tags": [
                    "Lead"
                ],
                "parameters": [
                    {
                        "type": "string",
                        "description": "Delete By ID",
                        "name": "id",
                        "in": "path",
                        "required": true
                    }
                ],
                "responses": {
                    "204": {
                        "description": "No Content"
                    }
                }
            }
        },
        "/notes": {
            "get": {
                "consumes": [
                    "application/json"
                ],
                "produces": [
                    "application/json"
                ],
                "tags": [
                    "Note"
                ],
                "parameters": [
                    {
                        "minimum": 10,
                        "type": "integer",
                        "name": "limit",
                        "in": "query"
                    },
                    {
                        "type": "string",
                        "name": "saleOpportunityId",
                        "in": "query",
                        "required": true
                    },
                    {
                        "minimum": 0,
                        "type": "integer",
                        "name": "skip",
                        "in": "query"
                    }
                ],
                "responses": {
                    "200": {
                        "description": "OK",
                        "schema": {
                            "$ref": "#/definitions/services.NotePagination"
                        }
                    }
                }
            },
            "post": {
                "consumes": [
                    "application/json"
                ],
                "produces": [
                    "application/json"
                ],
                "tags": [
                    "Note"
                ],
                "parameters": [
                    {
                        "description": "Create Note",
                        "name": "Note",
                        "in": "body",
                        "required": true,
                        "schema": {
                            "$ref": "#/definitions/validation.CreateNote"
                        }
                    }
                ],
                "responses": {
                    "200": {
                        "description": "OK",
                        "schema": {
                            "$ref": "#/definitions/entities.Note"
                        }
                    }
                }
            }
        },
        "/notes/{id}": {
            "get": {
                "consumes": [
                    "application/json"
                ],
                "produces": [
                    "application/json"
                ],
                "tags": [
                    "Note"
                ],
                "parameters": [
                    {
                        "type": "string",
                        "description": "Find Note By Id",
                        "name": "id",
                        "in": "path",
                        "required": true
                    }
                ],
                "responses": {
                    "200": {
                        "description": "OK",
                        "schema": {
                            "$ref": "#/definitions/entities.Note"
                        }
                    }
                }
            },
            "put": {
                "consumes": [
                    "application/json"
                ],
                "produces": [
                    "application/json"
                ],
                "tags": [
                    "Note"
                ],
                "parameters": [
                    {
                        "type": "string",
                        "description": "Update By ID",
                        "name": "id",
                        "in": "path",
                        "required": true
                    },
                    {
                        "description": "Update Note",
                        "name": "Note",
                        "in": "body",
                        "required": true,
                        "schema": {
                            "$ref": "#/definitions/validation.UpdateNote"
                        }
                    }
                ],
                "responses": {
                    "200": {
                        "description": "OK",
                        "schema": {
                            "$ref": "#/definitions/entities.Note"
                        }
                    }
                }
            },
            "delete": {
                "consumes": [
                    "application/json"
                ],
                "produces": [
                    "application/json"
                ],
                "tags": [
                    "Note"
                ],
                "parameters": [
                    {
                        "type": "string",
                        "description": "Delete By ID",
                        "name": "id",
                        "in": "path",
                        "required": true
                    }
                ],
                "responses": {
                    "204": {
                        "description": "No Content"
                    }
                }
            }
        },
        "/sale-opportunities": {
            "get": {
                "consumes": [
                    "application/json"
                ],
                "produces": [
                    "application/json"
                ],
                "tags": [
                    "SaleOpportunity"
                ],
                "parameters": [
                    {
                        "type": "string",
                        "name": "code",
                        "in": "query"
                    },
                    {
                        "type": "string",
                        "name": "employeeBys",
                        "in": "query"
                    },
                    {
                        "type": "string",
                        "name": "filterDateType",
                        "in": "query"
                    },
                    {
                        "type": "string",
                        "name": "fromDate",
                        "in": "query"
                    },
                    {
                        "type": "string",
                        "name": "groups",
                        "in": "query"
                    },
                    {
                        "type": "array",
                        "items": {
                            "type": "string"
                        },
                        "name": "includes",
                        "in": "query"
                    },
                    {
                        "type": "string",
                        "name": "lead",
                        "in": "query"
                    },
                    {
                        "minimum": 10,
                        "type": "integer",
                        "name": "limit",
                        "in": "query"
                    },
                    {
                        "type": "boolean",
                        "name": "onlyMe",
                        "in": "query"
                    },
                    {
                        "minimum": 0,
                        "type": "integer",
                        "name": "skip",
                        "in": "query"
                    },
                    {
                        "type": "string",
                        "name": "sources",
                        "in": "query"
                    },
                    {
                        "type": "string",
                        "name": "statuses",
                        "in": "query"
                    },
                    {
                        "type": "string",
                        "name": "storeCodes",
                        "in": "query"
                    },
                    {
                        "type": "string",
                        "name": "toDate",
                        "in": "query"
                    }
                ],
                "responses": {
                    "200": {
                        "description": "OK",
                        "schema": {
                            "$ref": "#/definitions/services.SaleOpportunityPagination"
                        }
                    }
                }
            },
            "post": {
                "consumes": [
                    "application/json"
                ],
                "produces": [
                    "application/json"
                ],
                "tags": [
                    "SaleOpportunity"
                ],
                "parameters": [
                    {
                        "description": "Create SaleOpportunity",
                        "name": "SaleOpportunity",
                        "in": "body",
                        "required": true,
                        "schema": {
                            "$ref": "#/definitions/validation.CreateSaleOpportunity"
                        }
                    }
                ],
                "responses": {
                    "200": {
                        "description": "OK",
                        "schema": {
                            "$ref": "#/definitions/entities.SaleOpportunity"
                        }
                    }
                }
            }
        },
        "/sale-opportunities/{id}": {
            "get": {
                "consumes": [
                    "application/json"
                ],
                "produces": [
                    "application/json"
                ],
                "tags": [
                    "SaleOpportunity"
                ],
                "parameters": [
                    {
                        "type": "string",
                        "description": "Find SaleOpportunity By ID",
                        "name": "id",
                        "in": "path",
                        "required": true
                    },
                    {
                        "type": "array",
                        "description": "includes",
                        "name": "includes",
                        "in": "query"
                    }
                ],
                "responses": {
                    "200": {
                        "description": "OK",
                        "schema": {
                            "$ref": "#/definitions/entities.SaleOpportunity"
                        }
                    }
                }
            },
            "put": {
                "consumes": [
                    "application/json"
                ],
                "produces": [
                    "application/json"
                ],
                "tags": [
                    "SaleOpportunity"
                ],
                "parameters": [
                    {
                        "type": "string",
                        "description": "Update By ID",
                        "name": "id",
                        "in": "path",
                        "required": true
                    },
                    {
                        "description": "Update SaleOpportunity",
                        "name": "SaleOpportunity",
                        "in": "body",
                        "required": true,
                        "schema": {
                            "$ref": "#/definitions/validation.UpdateSaleOpportunity"
                        }
                    }
                ],
                "responses": {
                    "200": {
                        "description": "OK",
                        "schema": {
                            "$ref": "#/definitions/entities.SaleOpportunity"
                        }
                    }
                }
            },
            "delete": {
                "consumes": [
                    "application/json"
                ],
                "produces": [
                    "application/json"
                ],
                "tags": [
                    "SaleOpportunity"
                ],
                "parameters": [
                    {
                        "type": "string",
                        "description": "Delete By ID",
                        "name": "id",
                        "in": "path",
                        "required": true
                    }
                ],
                "responses": {
                    "204": {
                        "description": "No Content"
                    }
                }
            }
        },
        "/sale-opportunities/{id}/logs": {
            "get": {
                "consumes": [
                    "application/json"
                ],
                "produces": [
                    "application/json"
                ],
                "tags": [
                    "SaleOpportunity"
                ],
                "parameters": [
                    {
                        "type": "string",
                        "description": "Get Logs By SaleOpportunity ID",
                        "name": "id",
                        "in": "path",
                        "required": true
                    },
                    {
                        "minimum": 10,
                        "type": "integer",
                        "name": "limit",
                        "in": "query"
                    },
                    {
                        "minimum": 0,
                        "type": "integer",
                        "name": "skip",
                        "in": "query"
                    }
                ],
                "responses": {
                    "200": {
                        "description": "OK",
                        "schema": {
                            "$ref": "#/definitions/services.SaleOpportunityLogsPagination"
                        }
                    }
                }
            }
        },
        "/statistics/employees": {
            "get": {
                "consumes": [
                    "application/json"
                ],
                "produces": [
                    "application/json"
                ],
                "tags": [
                    "Statistics"
                ],
                "parameters": [
                    {
                        "type": "array",
                        "items": {
                            "type": "string"
                        },
                        "name": "assetTypes",
                        "in": "query"
                    },
                    {
                        "type": "array",
                        "items": {
                            "type": "string"
                        },
                        "name": "employeeIds",
                        "in": "query",
                        "required": true
                    },
                    {
                        "type": "string",
                        "name": "fromDate",
                        "in": "query",
                        "required": true
                    },
                    {
                        "type": "array",
                        "items": {
                            "type": "string"
                        },
                        "name": "sources",
                        "in": "query"
                    },
                    {
                        "type": "array",
                        "items": {
                            "type": "string"
                        },
                        "name": "storeCodes",
                        "in": "query"
                    },
                    {
                        "type": "string",
                        "name": "toDate",
                        "in": "query",
                        "required": true
                    }
                ],
                "responses": {
                    "200": {
                        "description": "OK",
                        "schema": {
                            "type": "array",
                            "items": {
                                "$ref": "#/definitions/services.StatisticsEmployeeResponse"
                            }
                        }
                    }
                }
            }
        },
        "/statistics/index": {
            "get": {
                "consumes": [
                    "application/json"
                ],
                "produces": [
                    "application/json"
                ],
                "tags": [
                    "Statistics"
                ],
                "parameters": [
                    {
                        "type": "array",
                        "items": {
                            "type": "string"
                        },
                        "name": "assetTypes",
                        "in": "query"
                    },
                    {
                        "type": "string",
                        "name": "fromDate",
                        "in": "query",
                        "required": true
                    },
                    {
                        "type": "array",
                        "items": {
                            "type": "string"
                        },
                        "name": "sources",
                        "in": "query"
                    },
                    {
                        "type": "array",
                        "items": {
                            "type": "string"
                        },
                        "name": "storeCodes",
                        "in": "query"
                    },
                    {
                        "type": "string",
                        "name": "toDate",
                        "in": "query",
                        "required": true
                    }
                ],
                "responses": {
                    "200": {
                        "description": "OK",
                        "schema": {
                            "$ref": "#/definitions/services.StatisticsIndexResponse"
                        }
                    }
                }
            }
        },
        "/statistics/sources": {
            "get": {
                "consumes": [
                    "application/json"
                ],
                "produces": [
                    "application/json"
                ],
                "tags": [
                    "Statistics"
                ],
                "parameters": [
                    {
                        "type": "array",
                        "items": {
                            "type": "string"
                        },
                        "name": "assetTypes",
                        "in": "query"
                    },
                    {
                        "type": "string",
                        "name": "fromDate",
                        "in": "query",
                        "required": true
                    },
                    {
                        "type": "array",
                        "items": {
                            "type": "string"
                        },
                        "name": "sources",
                        "in": "query"
                    },
                    {
                        "type": "array",
                        "items": {
                            "type": "string"
                        },
                        "name": "storeCodes",
                        "in": "query"
                    },
                    {
                        "type": "string",
                        "name": "toDate",
                        "in": "query",
                        "required": true
                    }
                ],
                "responses": {
                    "200": {
                        "description": "OK",
                        "schema": {
                            "type": "array",
                            "items": {
                                "$ref": "#/definitions/services.StatisticsCommonResponse"
                            }
                        }
                    }
                }
            }
        },
        "/statistics/stores": {
            "get": {
                "consumes": [
                    "application/json"
                ],
                "produces": [
                    "application/json"
                ],
                "tags": [
                    "Statistics"
                ],
                "parameters": [
                    {
                        "type": "array",
                        "items": {
                            "type": "string"
                        },
                        "name": "assetTypes",
                        "in": "query"
                    },
                    {
                        "type": "string",
                        "name": "fromDate",
                        "in": "query",
                        "required": true
                    },
                    {
                        "type": "array",
                        "items": {
                            "type": "string"
                        },
                        "name": "sources",
                        "in": "query"
                    },
                    {
                        "type": "array",
                        "items": {
                            "type": "string"
                        },
                        "name": "storeCodes",
                        "in": "query"
                    },
                    {
                        "type": "string",
                        "name": "toDate",
                        "in": "query",
                        "required": true
                    }
                ],
                "responses": {
                    "200": {
                        "description": "OK",
                        "schema": {
                            "type": "array",
                            "items": {
                                "$ref": "#/definitions/services.StatisticsCommonResponse"
                            }
                        }
                    }
                }
            }
        },
        "/tags": {
            "get": {
                "consumes": [
                    "application/json"
                ],
                "produces": [
                    "application/json"
                ],
                "tags": [
                    "Tag"
                ],
                "responses": {
                    "200": {
                        "description": "OK",
                        "schema": {
                            "type": "array",
                            "items": {
                                "$ref": "#/definitions/entities.Tag"
                            }
                        }
                    }
                }
            }
        }
    },
    "definitions": {
        "entities.Asset": {
            "type": "object",
            "properties": {
                "assetType": {
                    "type": "string"
                },
                "demandLoan": {},
                "description": {
                    "type": "string"
                },
                "loanTerm": {},
                "media": {
                    "type": "array",
                    "items": {
                        "$ref": "#/definitions/entities.AssetMedia"
                    }
                }
            }
        },
        "entities.AssetMedia": {
            "type": "object",
            "properties": {
                "mimeType": {
                    "type": "string"
                },
                "url": {
                    "type": "string"
                }
            }
        },
        "entities.Lead": {
            "type": "object",
            "properties": {
                "address": {
                    "type": "string"
                },
                "birthday": {
                    "type": "string"
                },
                "createdAt": {
                    "type": "string"
                },
                "createdBy": {
                    "type": "string"
                },
                "customerId": {
                    "type": "string"
                },
                "deletedAt": {},
                "district": {
                    "type": "string"
                },
                "email": {
                    "type": "string"
                },
                "employeeBy": {
                    "type": "string"
                },
                "fullName": {
                    "type": "string"
                },
                "gender": {
                    "type": "string"
                },
                "id": {
                    "type": "string"
                },
                "nationalId": {
                    "type": "string"
                },
                "passportId": {
                    "type": "string"
                },
                "phone": {
                    "type": "string"
                },
                "province": {
                    "type": "string"
                },
                "source": {
                    "type": "string"
                },
                "storeCode": {
                    "type": "string"
                },
                "taxId": {
                    "type": "string"
                },
                "type": {
                    "$ref": "#/definitions/types.SaleOppType"
                },
                "updatedAt": {
                    "type": "string"
                },
                "updatedBy": {
                    "type": "string"
                }
            }
        },
        "entities.Log": {
            "type": "object",
            "properties": {
                "afterAttributes": {
                    "type": "object",
                    "additionalProperties": true
                },
                "beforeAttributes": {
                    "type": "object",
                    "additionalProperties": true
                },
                "createdAt": {
                    "type": "string"
                },
                "createdBy": {
                    "type": "string"
                },
                "id": {
                    "type": "string"
                },
                "saleOpportunityId": {
                    "type": "string"
                }
            }
        },
        "entities.Note": {
            "type": "object",
            "properties": {
                "content": {
                    "type": "string"
                },
                "createdAt": {
                    "type": "string"
                },
                "createdBy": {
                    "type": "string"
                },
                "deletedAt": {},
                "id": {
                    "type": "string"
                },
                "saleOpportunityId": {
                    "type": "string"
                },
                "updatedAt": {
                    "type": "string"
                },
                "updatedBy": {
                    "type": "string"
                }
            }
        },
        "entities.SaleOpportunity": {
            "type": "object",
            "properties": {
                "assets": {
                    "$ref": "#/definitions/entities.Asset"
                },
                "code": {
                    "type": "string"
                },
                "contractCode": {
                    "type": "string"
                },
                "created": {
                    "type": "string"
                },
                "createdAt": {
                    "type": "string"
                },
                "createdBy": {
                    "type": "string"
                },
                "deletedAt": {},
                "disbursedAmount": {
                    "type": "integer"
                },
                "disbursedAt": {
                    "type": "string"
                },
                "employee": {
                    "type": "string"
                },
                "employeeBy": {
                    "type": "string"
                },
                "group": {
                    "$ref": "#/definitions/types.SaleOppGroup"
                },
                "hash": {
                    "type": "string"
                },
                "id": {
                    "type": "string"
                },
                "lead": {
                    "description": "Include data when get sale opportunity",
                    "allOf": [
                        {
                            "$ref": "#/definitions/entities.Lead"
                        }
                    ]
                },
                "leadId": {
                    "type": "string"
                },
                "metadata": {
                    "type": "object",
                    "additionalProperties": true
                },
                "source": {
                    "type": "string"
                },
                "source_refs": {
                    "$ref": "#/definitions/entities.SourceRefs"
                },
                "status": {
                    "$ref": "#/definitions/types.SaleOppStatus"
                },
                "storeCode": {
                    "type": "string"
                },
                "tagData": {
                    "type": "array",
                    "items": {
                        "$ref": "#/definitions/entities.Tag"
                    }
                },
                "tags": {
                    "type": "array",
                    "items": {
                        "type": "string"
                    }
                },
                "type": {
                    "$ref": "#/definitions/types.SaleOppType"
                },
                "updated": {
                    "type": "string"
                },
                "updatedAt": {
                    "type": "string"
                },
                "updatedBy": {
                    "type": "string"
                }
            }
        },
        "entities.SourceRefs": {
            "type": "object",
            "properties": {
                "customerId": {},
                "refId": {
                    "type": "string"
                },
                "source": {
                    "type": "string"
                }
            }
        },
        "entities.Tag": {
            "type": "object",
            "properties": {
                "code": {
                    "type": "string"
                },
                "createdAt": {
                    "type": "string"
                },
                "id": {
                    "type": "string"
                },
                "name": {
                    "type": "string"
                }
            }
        },
        "services.LeadPagination": {
            "type": "object",
            "properties": {
                "limit": {
                    "type": "integer"
                },
                "list": {
                    "type": "array",
                    "items": {
                        "$ref": "#/definitions/entities.Lead"
                    }
                },
                "skip": {
                    "type": "integer"
                },
                "total": {
                    "type": "integer"
                }
            }
        },
        "services.NotePagination": {
            "type": "object",
            "properties": {
                "limit": {
                    "type": "integer"
                },
                "list": {
                    "type": "array",
                    "items": {
                        "$ref": "#/definitions/entities.Note"
                    }
                },
                "skip": {
                    "type": "integer"
                },
                "total": {
                    "type": "integer"
                }
            }
        },
        "services.SaleOpportunityLogsPagination": {
            "type": "object",
            "properties": {
                "limit": {
                    "type": "integer"
                },
                "list": {
                    "type": "array",
                    "items": {
                        "$ref": "#/definitions/entities.Log"
                    }
                },
                "skip": {
                    "type": "integer"
                },
                "total": {
                    "type": "integer"
                }
            }
        },
        "services.SaleOpportunityPagination": {
            "type": "object",
            "properties": {
                "limit": {
                    "type": "integer"
                },
                "list": {
                    "type": "array",
                    "items": {
                        "$ref": "#/definitions/entities.SaleOpportunity"
                    }
                },
                "skip": {
                    "type": "integer"
                },
                "total": {
                    "type": "integer"
                }
            }
        },
        "services.StatisticsCommonResponse": {
            "type": "object",
            "properties": {
                "code": {
                    "type": "string"
                },
                "details": {
                    "type": "array",
                    "items": {
                        "type": "object",
                        "properties": {
                            "data": {
                                "type": "array",
                                "items": {
                                    "type": "object",
                                    "properties": {
                                        "amount": {
                                            "type": "integer"
                                        },
                                        "group": {
                                            "$ref": "#/definitions/types.SaleOppGroup"
                                        },
                                        "order": {
                                            "type": "integer"
                                        }
                                    }
                                }
                            },
                            "order": {
                                "type": "integer"
                            },
                            "status": {
                                "$ref": "#/definitions/types.SaleOppStatus"
                            }
                        }
                    }
                }
            }
        },
        "services.StatisticsEmployeeResponse": {
            "type": "object",
            "properties": {
                "code": {
                    "type": "string"
                },
                "details": {
                    "type": "array",
                    "items": {
                        "type": "object",
                        "properties": {
                            "data": {
                                "type": "array",
                                "items": {
                                    "type": "object",
                                    "properties": {
                                        "amount": {
                                            "type": "integer"
                                        },
                                        "group": {
                                            "$ref": "#/definitions/types.SaleOppGroup"
                                        },
                                        "order": {
                                            "type": "integer"
                                        }
                                    }
                                }
                            },
                            "order": {
                                "type": "integer"
                            },
                            "status": {
                                "$ref": "#/definitions/types.SaleOppStatus"
                            }
                        }
                    }
                }
            }
        },
        "services.StatisticsIndexResponse": {
            "type": "object",
            "properties": {
                "denied": {
                    "type": "integer"
                },
                "disbursal": {
                    "type": "integer"
                },
                "disbursalAmount": {
                    "type": "integer"
                },
                "processing": {
                    "type": "integer"
                },
                "total": {
                    "type": "integer"
                }
            }
        },
        "types.SaleOppGroup": {
            "type": "string",
            "enum": [
                "OLD",
                "NEW"
            ],
            "x-enum-varnames": [
                "GroupOld",
                "GroupNew"
            ]
        },
        "types.SaleOppStatus": {
            "type": "string",
            "enum": [
                "NEW",
                "SUCCESS",
                "PENDING",
                "CONSULTING",
                "DEALT",
                "DENIED",
                "CANCEL",
                "UNCONTACTABLE",
                "created",
                "updated",
                "disbursed"
            ],
            "x-enum-varnames": [
                "SaleOppStatusNew",
                "SaleOppStatusSuccess",
                "SaleOppStatusPending",
                "SaleOppStatusConsulting",
                "SaleOppStatusDealt",
                "SaleOppStatusDenied",
                "SaleOppStatusCancel",
                "SaleOppStatusUnContactable",
                "FilterDateTypeCreatedAt",
                "FilterDateTypeUpdatedAt",
                "FilterDateTypeDisbursedAt"
            ]
        },
        "types.SaleOppType": {
            "type": "string",
            "enum": [
                "BORROWER",
                "PARTNER",
                "INVESTMENT"
            ],
            "x-enum-varnames": [
                "SaleOppTypeBorrower",
                "SaleOppTypePartner",
                "SaleOppTypeInvestment"
            ]
        },
        "validation.CreateLead": {
            "type": "object",
            "required": [
                "address",
                "birthday",
                "district",
                "email",
                "employeeBy",
                "fullName",
                "gender",
                "nationalId",
                "passportId",
                "phone",
                "province",
                "source",
                "storeCode",
                "taxId",
                "type"
            ],
            "properties": {
                "address": {
                    "type": "string"
                },
                "birthday": {
                    "type": "string"
                },
                "district": {
                    "type": "string"
                },
                "email": {
                    "type": "string"
                },
                "employeeBy": {
                    "type": "string"
                },
                "fullName": {
                    "type": "string"
                },
                "gender": {
                    "type": "string"
                },
                "nationalId": {
                    "type": "string"
                },
                "passportId": {
                    "type": "string"
                },
                "phone": {
                    "type": "string"
                },
                "province": {
                    "type": "string"
                },
                "source": {
                    "type": "string"
                },
                "storeCode": {
                    "type": "string"
                },
                "taxId": {
                    "type": "string"
                },
                "type": {
                    "$ref": "#/definitions/types.SaleOppType"
                }
            }
        },
        "validation.CreateNote": {
            "type": "object",
            "required": [
                "content",
                "saleOpportunityId"
            ],
            "properties": {
                "content": {
                    "type": "string"
                },
                "saleOpportunityId": {
                    "type": "string"
                }
            }
        },
        "validation.CreateSaleOpportunity": {
            "type": "object",
            "required": [
                "assets",
                "leadId",
                "source",
                "status",
                "type"
            ],
            "properties": {
                "assets": {
                    "$ref": "#/definitions/entities.Asset"
                },
                "employeeBy": {
                    "type": "string"
                },
                "group": {
                    "$ref": "#/definitions/types.SaleOppGroup"
                },
                "leadId": {
                    "type": "string"
                },
                "note": {
                    "type": "string"
                },
                "source": {
                    "type": "string"
                },
                "status": {
                    "$ref": "#/definitions/types.SaleOppStatus"
                },
                "storeCode": {
                    "type": "string"
                },
                "tags": {
                    "type": "array",
                    "items": {
                        "type": "string"
                    }
                },
                "type": {
                    "$ref": "#/definitions/types.SaleOppType"
                }
            }
        },
        "validation.UpdateLead": {
            "type": "object",
            "required": [
                "fullName"
            ],
            "properties": {
                "address": {
                    "type": "string"
                },
                "birthday": {
                    "type": "string"
                },
                "district": {
                    "type": "string"
                },
                "email": {
                    "type": "string"
                },
                "employeeBy": {
                    "type": "string"
                },
                "fullName": {
                    "type": "string"
                },
                "gender": {
                    "type": "string"
                },
                "nationalId": {
                    "type": "string"
                },
                "passportId": {
                    "type": "string"
                },
                "phone": {
                    "type": "string"
                },
                "province": {
                    "type": "string"
                },
                "source": {
                    "type": "string"
                },
                "storeCode": {
                    "type": "string"
                },
                "taxId": {
                    "type": "string"
                },
                "type": {
                    "$ref": "#/definitions/types.SaleOppType"
                }
            }
        },
        "validation.UpdateNote": {
            "type": "object",
            "properties": {
                "content": {
                    "type": "string"
                }
            }
        },
        "validation.UpdateSaleOpportunity": {
            "type": "object",
            "properties": {
                "assets": {
                    "$ref": "#/definitions/entities.Asset"
                },
                "contractCode": {
                    "type": "string"
                },
                "employeeBy": {
                    "type": "string"
                },
                "group": {
                    "$ref": "#/definitions/types.SaleOppGroup"
                },
                "leadId": {
                    "type": "string"
                },
                "source": {
                    "type": "string"
                },
                "status": {
                    "$ref": "#/definitions/types.SaleOppStatus"
                },
                "storeCode": {
                    "type": "string"
                },
                "tags": {
                    "type": "array",
                    "items": {
                        "type": "string"
                    }
                },
                "type": {
                    "$ref": "#/definitions/types.SaleOppType"
                }
            }
        }
    }
}